{
    "version": 1,
    "revision": 0,
    "rules": [
        {
            "primary-output": "x64\\Debug\\SystemGLStringUtil.h.obj",
            "outputs": [
                "C:\\Users\\chris\\source\\repos\\SystemGL\\SystemGL\\x64\\Debug\\vc145.pdb",
                "x64\\Debug\\",
                "C:\\Users\\chris\\source\\repos\\SystemGL\\SystemGL\\x64\\Debug\\SystemGLStringUtil.h.ifc"
            ],
            "provides": [
                {
                    "logical-name": "include\\SystemGLStringUtil.h",
                    "source-path": "c:\\users\\chris\\source\\repos\\systemgl\\systemgl\\include\\systemglstringutil.h",
                    "lookup-method": "absolute"
                }
            ],
            "requires": []
        }
    ]
}